sql_cache_package/__init__.py
sql_cache_package/cache.py
sql_cache_package/database.py
sql_cache_package/main.py
sql_cache_package-0.1.dist-info/METADATA
sql_cache_package-0.1.dist-info/WHEEL
sql_cache_package-0.1.dist-info/entry_points.txt
sql_cache_package-0.1.dist-info/license
sql_cache_package-0.1.dist-info/top_level.txt
sql_cache_package-0.1.dist-info/RECORD
